based_indexing/__init__.py
based_indexing/based.py
based_indexing-0.1.1.dist-info/LICENSE
based_indexing-0.1.1.dist-info/METADATA
based_indexing-0.1.1.dist-info/WHEEL
based_indexing-0.1.1.dist-info/RECORD
